odoo9_addon_website_blog_share-9.0.1.0.0-py2.7-nspkg.pth
odoo9_addon_website_blog_share-9.0.1.0.0.dist-info/top_level.txt
odoo9_addon_website_blog_share-9.0.1.0.0.dist-info/WHEEL
odoo9_addon_website_blog_share-9.0.1.0.0.dist-info/RECORD
odoo9_addon_website_blog_share-9.0.1.0.0.dist-info/metadata.json
odoo9_addon_website_blog_share-9.0.1.0.0.dist-info/DESCRIPTION.rst
odoo9_addon_website_blog_share-9.0.1.0.0.dist-info/METADATA
odoo9_addon_website_blog_share-9.0.1.0.0.dist-info/namespace_packages.txt
odoo_addons/website_blog_share/__openerp__.py
odoo_addons/website_blog_share/__init__.py
odoo_addons/website_blog_share/README.rst
odoo_addons/website_blog_share/i18n/it.po
odoo_addons/website_blog_share/i18n/es.po
odoo_addons/website_blog_share/i18n/ca.po
odoo_addons/website_blog_share/i18n/sl.po
odoo_addons/website_blog_share/i18n/de.po
odoo_addons/website_blog_share/i18n/fr.po
odoo_addons/website_blog_share/i18n/pt_BR.po
odoo_addons/website_blog_share/i18n/el_GR.po
odoo_addons/website_blog_share/views/website_blog.xml
odoo_addons/website_blog_share/static/description/icon.png
