Metadata-Version: 2.0
Name: odoo9-addon-website-blog-share
Version: 9.0.1.0.0
Summary: Blog Share
Home-page: https://tecnativa.com
Author: Andhitia Rama, Tecnativa,Odoo Community Association (OCA)
Author-email: support@odoo-community.org
License: AGPL-3
Platform: UNKNOWN
Requires-Dist: odoo (<9.1a,>=9.0a)
Classifier: Programming Language :: Python :: 2.7
Classifier: Framework :: Odoo
Classifier: License :: OSI Approved :: GNU Affero General Public License v3
